wavegui/__init__.py
wavegui/core.py
wavegui/exception.py
wavegui/graphics.py
wavegui/main.py
wavegui/routing.py
wavegui/session.py
wavegui/task.py
wavegui/template.py
wavegui/types.py
wavegui/ui.py
wavegui/ui_ext.py
wavegui/utils.py
wavegui/www/asset-manifest.json
wavegui/www/favicon.ico
wavegui/www/index.html
wavegui/www/logo192.png
wavegui/www/logo512.png
wavegui/www/manifest.json
wavegui/www/precache-manifest.586ad9b1fa781a77da59e6fa5b1d7db9.js
wavegui/www/robots.txt
wavegui/www/service-worker.js
wavegui/www/static/LocalizationProvider-legacy.f03966f6.js
wavegui/www/static/LocalizationProvider.44110c99.js
wavegui/www/static/Paper-legacy.c6641457.js
wavegui/www/static/Paper.b0a60de2.js
wavegui/www/static/index-legacy.2f28cb95.js
wavegui/www/static/index-legacy.37bb79e0.js
wavegui/www/static/index-legacy.46ab5d05.js
wavegui/www/static/index-legacy.569d8633.js
wavegui/www/static/index-legacy.5a1ebdf4.js
wavegui/www/static/index-legacy.a148bce7.js
wavegui/www/static/index-legacy.b61be0bc.js
wavegui/www/static/index.10e23dcf.js
wavegui/www/static/index.32208328.js
wavegui/www/static/index.5fd03832.css
wavegui/www/static/index.6d97a6f7.js
wavegui/www/static/index.8cd79a25.js
wavegui/www/static/index.9f6e68e5.js
wavegui/www/static/index.ce1f283d.js
wavegui/www/static/index.d70e8ca0.js
wavegui/www/static/inter-100.98b515d8.ttf
wavegui/www/static/inter-200.81e7bd41.ttf
wavegui/www/static/inter-300.26a78cc7.ttf
wavegui/www/static/inter-400.494a9c88.ttf
wavegui/www/static/inter-500.a0b1f949.ttf
wavegui/www/static/inter-600.f036a457.ttf
wavegui/www/static/inter-700.2ad83f24.ttf
wavegui/www/static/inter-800.6fb3140d.ttf
wavegui/www/static/inter-900.3c163d15.ttf
wavegui/www/static/polyfills-legacy.13970731.js
wavegui/www/static/useThemeProps-legacy.9a6aaf7f.js
wavegui/www/static/useThemeProps.b60c7b26.js
wavegui/www/static/vega-embed.module-legacy.2ea1948d.js
wavegui/www/static/vega-embed.module.06bc0aae.js
wavegui/www/static/vega.module-legacy.4bd35772.js
wavegui-1.0.dist-info/LICENSE
wavegui-1.0.dist-info/METADATA
wavegui-1.0.dist-info/WHEEL
wavegui-1.0.dist-info/top_level.txt
wavegui-1.0.dist-info/RECORD
