Metadata-Version: 2.1
Name: wavegui
Version: 1.0
Summary: web based ui framework, write pretty ui without knoledge of css/html.
Home-page: https://github.com/pyflow/wavegui/
Author: Wei Zhuo
Author-email: zeaphoo@qq.com
License: MIT
Platform: any
Classifier: Development Status :: 4 - Beta
Classifier: Environment :: Web Environment
Classifier: Intended Audience :: Developers
Classifier: License :: OSI Approved :: MIT License
Classifier: Operating System :: OS Independent
Classifier: Programming Language :: Python
Classifier: Programming Language :: Python :: 3
Classifier: Programming Language :: Python :: 3.7
Classifier: Programming Language :: Python :: 3.8
Classifier: Programming Language :: Python :: 3.9
Classifier: Topic :: Software Development :: Libraries :: Python Modules
Requires-Python: >=3.7
License-File: LICENSE
Requires-Dist: basepy >=0.3.4
Requires-Dist: starlette >=0.13.8
Requires-Dist: uvicorn[standard] >=0.12.2
Requires-Dist: itsdangerous
Requires-Dist: aiofiles
Requires-Dist: python-multipart
Provides-Extra: test
Requires-Dist: pytest >=3 ; extra == 'test'
